continuous_integration/environment-3.10.yml
continuous_integration/environment-3.11.yml
continuous_integration/environment-3.12.yml
continuous_integration/environment-3.9.yml
continuous_integration/environment-doc.yml
continuous_integration/environment-latest.yml
continuous_integration/gpuci/axis.yaml
continuous_integration/gpuci/build.sh
dask_image/__init__.py
dask_image/_version.py
dask_image/dispatch/__init__.py
dask_image/dispatch/_dispatch_ndfilters.py
dask_image/dispatch/_dispatch_ndinterp.py
dask_image/dispatch/_dispatch_ndmorph.py
dask_image/dispatch/_dispatcher.py
dask_image/dispatch/_utils.py
dask_image/imread/__init__.py
dask_image/ndfilters/__init__.py
dask_image/ndfilters/_conv.py
dask_image/ndfilters/_diff.py
dask_image/ndfilters/_edge.py
dask_image/ndfilters/_gaussian.py
dask_image/ndfilters/_generic.py
dask_image/ndfilters/_order.py
dask_image/ndfilters/_smooth.py
dask_image/ndfilters/_threshold.py
dask_image/ndfilters/_utils.py
dask_image/ndfourier/__init__.py
dask_image/ndfourier/_utils.py
dask_image/ndinterp/__init__.py
dask_image/ndmeasure/__init__.py
dask_image/ndmeasure/_utils/__init__.py
dask_image/ndmeasure/_utils/_find_objects.py
dask_image/ndmeasure/_utils/_label.py
dask_image/ndmorph/__init__.py
dask_image/ndmorph/_ops.py
dask_image/ndmorph/_utils.py
docs/Makefile
docs/api.rst
docs/authors.rst
docs/conf.py
docs/contributing.rst
docs/coverage.rst
docs/history.rst
docs/index.rst
docs/installation.rst
docs/make.bat
docs/quickstart.rst
docs/release/generate_release_notes.py
docs/release/release_guide.rst
dask_image-2024.5.3.dist-info/LICENSE.txt
dask_image-2024.5.3.dist-info/METADATA
dask_image-2024.5.3.dist-info/WHEEL
dask_image-2024.5.3.dist-info/top_level.txt
dask_image-2024.5.3.dist-info/RECORD
