Metadata-Version: 2.1
Name: dask-image
Version: 2024.5.3
Summary: Distributed image processing
Author: dask-image contributors. see https://github.com/dask/dask-image/graphs/contributors
License: BSD-3-Clause
Project-URL: Homepage, https://image.dask.org
Project-URL: Issue Tracker, https://github.com/dask/dask-image/issues
Project-URL: Source Code, https://github.com/dask/dask-image
Keywords: dask-image,dask,image
Classifier: Development Status :: 2 - Pre-Alpha
Classifier: Intended Audience :: Developers
Classifier: License :: OSI Approved :: BSD License
Classifier: Natural Language :: English
Classifier: Operating System :: OS Independent
Classifier: Programming Language :: Python :: 3
Classifier: Programming Language :: Python :: 3.9
Classifier: Programming Language :: Python :: 3.10
Classifier: Programming Language :: Python :: 3.11
Classifier: Programming Language :: Python :: 3.12
Requires-Python: >=3.9
License-File: LICENSE.txt
Requires-Dist: dask[array,dataframe]>=2024.4.1
Requires-Dist: numpy>=1.18
Requires-Dist: scipy>=1.7.0
Requires-Dist: pandas>=2.0.0
Requires-Dist: pims>=0.4.1
Requires-Dist: tifffile>=2018.10.18
Provides-Extra: test
Requires-Dist: build>=1.2.1; extra == "test"
Requires-Dist: coverage>=7.2.1; extra == "test"
Requires-Dist: flake8>=6.0.0; extra == "test"
Requires-Dist: Flake8-pyproject; extra == "test"
Requires-Dist: pytest>=7.2.2; extra == "test"
Requires-Dist: pytest-cov>=4.0.0; extra == "test"
Requires-Dist: pytest-flake8>=1.1.1; extra == "test"
Requires-Dist: pytest-timeout>=2.3.1; extra == "test"
Requires-Dist: twine>=3.1.1; extra == "test"
Provides-Extra: gpu
Requires-Dist: cupy>=9.0.0; extra == "gpu"
